quiet/__init__.py
quiet/libquiet.so
quiet/quiet-profiles.json
quiet/quiet.py
dataos-0.1.dist-info/METADATA
dataos-0.1.dist-info/WHEEL
dataos-0.1.dist-info/top_level.txt
dataos-0.1.dist-info/RECORD
