Metadata-Version: 2.1
Name: dataos
Version: 0.1
Summary: Quiet Modem, to transmit data with sound
Home-page: https://github.com/quiet/quiet.py
Author: Brian Armstrong, Yihui Xiong
Author-email: brian.armstrong.ece+pypi@gmail.com
License: UNKNOWN
Platform: UNKNOWN
Requires-Dist: numpy
